rest_framework_enhanced/__init__.py
rest_framework_enhanced/content_negotiation.py
rest_framework_enhanced/exceptions.py
rest_framework_enhanced/generics.py
rest_framework_enhanced/mixins.py
rest_framework_enhanced/pagination.py
rest_framework_enhanced/response.py
rest_framework_enhanced/urls.py
rest_framework_enhanced/viewsets.py
rest_framework_enhanced/management/__init__.py
rest_framework_enhanced/management/commands/__init__.py
rest_framework_enhanced/management/commands/setupsettings.py
rest_framework_enhanced/management/commands/startdrfapp.py
rest_framework_enhanced/template/default_settings.txt
rest_framework_enhanced/template/drf_app/__init__.py-tpl
rest_framework_enhanced/template/drf_app/admin.py-tpl
rest_framework_enhanced/template/drf_app/apps.py-tpl
rest_framework_enhanced/template/drf_app/models.py-tpl
rest_framework_enhanced/template/drf_app/serializers.py-tpl
rest_framework_enhanced/template/drf_app/urls.py-tpl
rest_framework_enhanced/template/drf_app/views.py-tpl
rest_framework_enhanced/template/drf_app/migrations/__init__.py-tpl
djangorestframework_enhanced-0.0.1.dist-info/LICENSE
djangorestframework_enhanced-0.0.1.dist-info/METADATA
djangorestframework_enhanced-0.0.1.dist-info/WHEEL
djangorestframework_enhanced-0.0.1.dist-info/top_level.txt
djangorestframework_enhanced-0.0.1.dist-info/RECORD
